puppetmaster/__init__.py
puppetmaster/assertions.py
puppetmaster/core.py
puppetmaster/exceptions.py
puppetmaster/form_filling.py
puppetmaster/middleware.py
puppetmaster/waiter.py
puppetmaster/kobotoolbox/__init__.py
puppetmaster/kobotoolbox/assertions.py
puppetmaster/kobotoolbox/core.py
puppetmaster/kobotoolbox/form_filling.py
puppet_master-0.1.0.dist-info/LICENSE
puppet_master-0.1.0.dist-info/METADATA
puppet_master-0.1.0.dist-info/WHEEL
puppet_master-0.1.0.dist-info/top_level.txt
puppet_master-0.1.0.dist-info/RECORD
