Metadata-Version: 2.1
Name: puppet-master
Version: 0.1.0
Summary: UNKNOWN
Home-page: https://github.com/qedsoftware/puppet-master
Author: Quantitative Engineering Design Inc.
Author-email: info@qed.ai
License: MIT
Keywords: puppet selenium form filling driver
Platform: UNKNOWN
Classifier: Development Status :: 3 - Alpha
Classifier: Intended Audience :: Developers
Classifier: License :: OSI Approved :: MIT License
Classifier: Programming Language :: Python :: 3.6
Classifier: Programming Language :: Python :: 3.7
